aerium_jsonrpc/__init__.py
aerium_jsonrpc/client.py
aerium_jsonrpc/models.py
aerium_jsonrpc-0.2.0.dist-info/licenses/LICENSE
aerium_jsonrpc-0.2.0.dist-info/METADATA
aerium_jsonrpc-0.2.0.dist-info/WHEEL
aerium_jsonrpc-0.2.0.dist-info/top_level.txt
aerium_jsonrpc-0.2.0.dist-info/RECORD
