Metadata-Version: 2.4
Name: aerium-jsonrpc
Version: 0.2.0
Summary: Python client for interacting with the Aerium blockchain via JSON-RPC
Home-page: https://aerium.network
Author: Aerium Development Team
Author-email: info@aerium.network
License: MIT
Keywords: aerium,blockchain,json-rpc
Classifier: Development Status :: 5 - Production/Stable
Classifier: Intended Audience :: Developers
Classifier: Topic :: Software Development :: Build Tools
Classifier: Operating System :: OS Independent
Requires-Python: >=3.6
License-File: LICENSE
Requires-Dist: jsonrpc2-pyclient>=5.2.0
Requires-Dist: py-undefined>=0.1.5
Requires-Dist: pydantic>=2.5.3
Dynamic: author
Dynamic: author-email
Dynamic: classifier
Dynamic: description
Dynamic: description-content-type
Dynamic: home-page
Dynamic: keywords
Dynamic: license
Dynamic: license-file
Dynamic: requires-dist
Dynamic: requires-python
Dynamic: summary
